gpt/__init__.py
gpt/gpt.py
gpt_magic-0.2.0.dist-info/LICENSE
gpt_magic-0.2.0.dist-info/METADATA
gpt_magic-0.2.0.dist-info/WHEEL
gpt_magic-0.2.0.dist-info/top_level.txt
gpt_magic-0.2.0.dist-info/RECORD
