Metadata-Version: 2.1
Name: gpt-magic
Version: 0.2.0
Summary: A Jupyter/IPython magic command for generating code using GPT.
Author-email: BIFF <info@biff.ai>
License: MIT License
Project-URL: Homepage, https://biff.ai/bif-0003
Keywords: jupyter,ipython,gpt,ai
Classifier: License :: OSI Approved :: MIT License
Classifier: Programming Language :: Python :: 3
Requires-Python: >=3.6
License-File: LICENSE
Requires-Dist: openai
Requires-Dist: requests
Provides-Extra: dev
Requires-Dist: pytest ; extra == 'dev'
Requires-Dist: pytest-mock ; extra == 'dev'
Requires-Dist: requests-mock ; extra == 'dev'
Requires-Dist: notebook ; extra == 'dev'
Requires-Dist: python-dotenv ; extra == 'dev'
Provides-Extra: test
Requires-Dist: pytest ; extra == 'test'
Requires-Dist: pytest-mock ; extra == 'test'
Requires-Dist: requests-mock ; extra == 'test'
Requires-Dist: notebook ; extra == 'test'
Requires-Dist: python-dotenv ; extra == 'test'
